{"tournamentId":{"name":"worldt20-2016","id":3783},"groups":[{"groupName":"Knockouts"},{"standings":[{"played":0,"won":0,"lost":0,"tied":0,"points":0,"noResult":0,"positionLabel":"1","netRunRate":"+0.000","position":1,"team":{"shortName":"England","primaryColor":"023B7A","secondaryColor":"E62102","abbreviation":"ENG","type":"m","fullName":"England","id":11},"recentForm":[],"bowlAvg":"Infinity"},{"played":0,"won":0,"lost":0,"tied":0,"points":0,"noResult":0,"positionLabel":"2","netRunRate":"+0.000","position":2,"team":{"shortName":"South Africa","primaryColor":"FFCD00","secondaryColor":"0E4D05","abbreviation":"SA","type":"m","fullName":"South Africa","id":19},"recentForm":[],"bowlAvg":"Infinity"},{"played":0,"won":0,"lost":0,"tied":0,"points":0,"noResult":0,"positionLabel":"3","netRunRate":"+0.000","position":3,"team":{"shortName":"Sri Lanka","primaryColor":"02ABDC","secondaryColor":"737D1D","abbreviation":"SL","type":"m","fullName":"Sri Lanka","id":13},"recentForm":[],"bowlAvg":"Infinity"},{"played":0,"won":0,"lost":0,"tied":0,"points":0,"noResult":0,"positionLabel":"4","netRunRate":"+0.000","position":4,"team":{"shortName":"TBD (B1)","primaryColor":"FFFFFF","secondaryColor":"FFFFFF","abbreviation":"TBDb1","fullName":"TBD (B1)","id":390},"recentForm":[],"bowlAvg":"Infinity"},{"played":0,"won":0,"lost":0,"tied":0,"points":0,"noResult":0,"positionLabel":"5","netRunRate":"+0.000","position":5,"team":{"shortName":"West Indies","primaryColor":"8C0253","secondaryColor":"5C1515","abbreviation":"WI","type":"m","fullName":"West Indies","id":21},"recentForm":[],"bowlAvg":"Infinity"}],"groupName":"Group 1"},{"standings":[{"played":0,"won":0,"lost":0,"tied":0,"points":0,"noResult":0,"positionLabel":"1","netRunRate":"+0.000","position":1,"team":{"shortName":"Australia","primaryColor":"7DBD18","secondaryColor":"D6CF00","abbreviation":"AUS","type":"m","fullName":"Australia","id":15},"recentForm":[],"bowlAvg":"Infinity"},{"played":0,"won":0,"lost":0,"tied":0,"points":0,"noResult":0,"positionLabel":"2","netRunRate":"+0.000","position":2,"team":{"shortName":"India","primaryColor":"FD6205","secondaryColor":"3A5BFD","abbreviation":"IND","type":"m","fullName":"India","id":14},"recentForm":[],"bowlAvg":"Infinity"},{"played":0,"won":0,"lost":0,"tied":0,"points":0,"noResult":0,"positionLabel":"3","netRunRate":"+0.000","position":3,"team":{"shortName":"New Zealand","primaryColor":"012247","secondaryColor":"FAFAFA","abbreviation":"NZ","type":"m","fullName":"New Zealand","id":16},"recentForm":[],"bowlAvg":"Infinity"},{"played":0,"won":0,"lost":0,"tied":0,"points":0,"noResult":0,"positionLabel":"4","netRunRate":"+0.000","position":4,"team":{"shortName":"Pakistan","primaryColor":"084B01","secondaryColor":"4B4407","abbreviation":"PAK","type":"m","fullName":"Pakistan","id":20},"recentForm":[],"bowlAvg":"Infinity"},{"played":0,"won":0,"lost":0,"tied":0,"points":0,"noResult":0,"positionLabel":"5","netRunRate":"+0.000","position":5,"team":{"shortName":"TBD (A1)","primaryColor":"FFFFFF","secondaryColor":"FFFFFF","abbreviation":"TBDa1","fullName":"TBD (A1)","id":389},"recentForm":[],"bowlAvg":"Infinity"}],"groupName":"Group 2"},{"standings":[{"played":0,"won":0,"lost":0,"tied":0,"points":0,"noResult":0,"positionLabel":"1","netRunRate":"+0.000","position":1,"team":{"shortName":"Afghanistan","primaryColor":"000000","secondaryColor":"000000","abbreviation":"AFG","type":"m","fullName":"Afghanistan","id":17},"recentForm":[],"bowlAvg":"Infinity"},{"played":0,"won":0,"lost":0,"tied":0,"points":0,"noResult":0,"positionLabel":"2","netRunRate":"+0.000","position":2,"team":{"shortName":"Hong Kong","primaryColor":"1A1617","secondaryColor":"FFFFFF","abbreviation":"HK","type":"m","fullName":"Hong Kong","id":103},"recentForm":[],"bowlAvg":"Infinity"},{"played":0,"won":0,"lost":0,"tied":0,"points":0,"noResult":0,"positionLabel":"3","netRunRate":"+0.000","position":3,"team":{"shortName":"Scotland","primaryColor":"003777","secondaryColor":"FFFFFF","abbreviation":"SCO","type":"m","fullName":"Scotland","id":69},"recentForm":[],"bowlAvg":"Infinity"},{"played":0,"won":0,"lost":0,"tied":0,"points":0,"noResult":0,"positionLabel":"4","netRunRate":"+0.000","position":4,"team":{"shortName":"Zimbabwe","primaryColor":"546C87","secondaryColor":"FF0000","abbreviation":"ZIM","type":"m","fullName":"Zimbabwe","id":18},"recentForm":[],"bowlAvg":"Infinity"}],"groupName":"Group B"},{"standings":[{"played":0,"won":0,"lost":0,"tied":0,"points":0,"noResult":0,"positionLabel":"1","netRunRate":"+0.000","position":1,"team":{"shortName":"Bangladesh","primaryColor":"04A093","secondaryColor":"04A093","abbreviation":"BAN","type":"m","fullName":"Bangladesh","id":22},"recentForm":[],"bowlAvg":"Infinity"},{"played":0,"won":0,"lost":0,"tied":0,"points":0,"noResult":0,"positionLabel":"2","netRunRate":"+0.000","position":2,"team":{"shortName":"Ireland","primaryColor":"467101","secondaryColor":"FFFFFF","abbreviation":"IRE","type":"m","fullName":"Ireland","id":12},"recentForm":[],"bowlAvg":"Infinity"},{"played":0,"won":0,"lost":0,"tied":0,"points":0,"noResult":0,"positionLabel":"3","netRunRate":"+0.000","position":3,"team":{"shortName":"Netherlands","primaryColor":"EA800C","secondaryColor":"FFFFFF","abbreviation":"NET","type":"m","fullName":"Netherlands","id":68},"recentForm":[],"bowlAvg":"Infinity"},{"played":0,"won":0,"lost":0,"tied":0,"points":0,"noResult":0,"positionLabel":"4","netRunRate":"+0.000","position":4,"team":{"shortName":"Oman","primaryColor":"FFFFFF","secondaryColor":"FFFFFF","abbreviation":"OMA","type":"m","fullName":"Oman","id":128},"recentForm":[],"bowlAvg":"Infinity"}],"groupName":"Group A"}]}